Metadata-Version: 2.1
Name: term2md
Version: 0.3.4
Summary: convert ANSI terminal control characters to Markdown
Home-page: https://github.com/jonm/term2md
Author: Jon Moore
License: MIT
Keywords: text terminal ansi control markdown
Platform: UNKNOWN
Classifier: Programming Language :: Python :: 3
Classifier: License :: OSI Approved :: MIT License
Classifier: Operating System :: OS Independent
Classifier: Development Status :: 3 - Alpha
Classifier: Intended Audience :: Developers
Classifier: Topic :: Text Processing :: Filters
